clean_enoa/__init__.py
clean_enoa/call_inegi.py
clean_enoa-0.1.1.dist-info/LICENSE
clean_enoa-0.1.1.dist-info/WHEEL
clean_enoa-0.1.1.dist-info/METADATA
clean_enoa-0.1.1.dist-info/RECORD
