Metadata-Version: 2.1
Name: clean_enoa
Version: 0.1.1
Summary: This package makes requests to INEGI about unemployment in Mexico
Home-page: https://github.com/nepito/clean-enoa
Author: Nepo Rojas • GECI
Author-email: nepo.rojas@islas.org.mx
Requires-Python: >=3
Classifier: License :: OSI Approved :: GNU General Public License v3 or later (GPLv3+)
Classifier: Programming Language :: Python :: 3.7
Classifier: Programming Language :: Python :: 3.8
Classifier: Programming Language :: Python :: 3.9
Requires-Dist: requests
